{
  "schema": "game.core_loop",
  "project": "mine-cards",
  "status": "base_mining_v001",
  "hook": "Train a blocky miner through one idle Mining activity, gather ore, upgrade the pickaxe, and unlock deeper mine nodes.",
  "loop": [
    {
      "step": "choose_node",
      "player_intent": "Pick the best currently available mining target.",
      "input": "select_mining_node",
      "feedback": "Selected node highlights and shows yield, interval, XP, and next unlock.",
      "blocked_state": "Locked nodes show the missing Mining level or tool requirement."
    },
    {
      "step": "mine_tick",
      "player_intent": "Let the active action complete.",
      "input": "wait_or_keep_activity_running",
      "output_number": "ore_delta, mining_xp_delta, mastery_xp_delta, coin_chance",
      "feedback": "Progress bar fills, miner animation strikes the node, reward log updates.",
      "failure_state": "No failure in v0.01; mining is a safe idle activity."
    },
    {
      "step": "rare_event",
      "player_intent": "Notice and optionally claim a short bonus.",
      "input": "tap_geode_or_continue",
      "output_number": "bonus_ore_or_coins",
      "feedback": "A geode/rich-vein callout appears with a clear timer or claim state.",
      "blocked_state": "If the event hides the core progress bar or confuses the main action, remove it."
    },
    {
      "step": "upgrade_pickaxe",
      "player_intent": "Spend gathered value to improve future mining.",
      "input": "tap_upgrade_pickaxe",
      "currency_sink": "ore_and_or_coins",
      "feedback": "Before/after interval or yield change is shown.",
      "blocked_state": "Unaffordable upgrade shows exact missing resource."
    },
    {
      "step": "unlock_deeper_node",
      "player_intent": "Move from starter mining to a better target.",
      "input": "reach_level_or_tool_requirement",
      "feedback": "New node unlock animation and node list update.",
      "blocked_state": "Next locked node remains visible with a simple requirement."
    }
  ],
  "first_slice_system_map": {
    "primary_action": "select_or_continue_mining_node",
    "passive_or_idle_action": "mining_progress_timer",
    "activity": "mining",
    "upgrade": "pickaxe",
    "stats_affected": ["mining_level", "node_mastery", "ore", "coins", "mining_interval"],
    "currency_source": "mining_ticks_and_rare_geodes",
    "currency_sink": "pickaxe_upgrade",
    "unlock": "copper_vein_or_tin_vein",
    "visual_status_change": "node_highlight, progress_bar, miner_animation, reward_log, upgrade_before_after",
    "reason_to_return": "mine faster, unlock deeper nodes, prepare future smithing/combat"
  },
  "reference_grounding": {
    "status": "early_history_deconstruction_available",
    "source_packet": [
      "references/melvor_idle_reference_intake_2026-06-17.md",
      "references/melvor_history_deconstruction_2026-06-17.md"
    ],
    "parameter_source": "data/parameters.json",
    "needed_before_runtime_claims": [
      "final v0.01 numbers reviewed",
      "native fake-shot-to-screenshot visual gate",
      "public-safe original voxel hero decision"
    ]
  }
}
