{
  "schema": "ai_studio.asset_records.v1",
  "scope": "ai-studio:preview-hdr",
  "assets": [
    {
      "asset_id": "studio-env-hdr",
      "path": "ai_studio/assets/previews/studio_env.hdr",
      "classification": "generated-procedural-output",
      "origin": "mine",
      "provenance": "generated deterministically by ai_studio/assets/previews/make_studio_hdr.py; lead disposition 2026-07-12",
      "source_page": "ai_studio/assets/previews/make_studio_hdr.py",
      "license": "Studio-Owned-Public-1.0",
      "license_kind": "custom",
      "publish": "true",
      "redistribution_allowed": "true",
      "sha256": "6249d61cb8e5534e6396a888b45732ab93716820a13b4ace7cd53d1565c90361",
      "bytes": 2097202,
      "commercial_use": "true",
      "modification_allowed": "true",
      "attribution_required": "false",
      "notice_required": "false",
      "author_vendor": "Neotolis Studio",
      "license_file": "ai_studio/assets/manifests/PROJECT_OUTPUT_LICENSE.md"
    }
  ]
}
